cdk_integ_runner_cwd_fix/__init__.py
cdk_integ_runner_cwd_fix/fix.py
cdk_integ_runner_cwd_fix-0.1.1.dist-info/LICENSE.md
cdk_integ_runner_cwd_fix-0.1.1.dist-info/METADATA
cdk_integ_runner_cwd_fix-0.1.1.dist-info/WHEEL
cdk_integ_runner_cwd_fix-0.1.1.dist-info/RECORD
