Metadata-Version: 2.1
Name: cdk-integ-runner-cwd-fix
Version: 0.1.1
Summary: Fix the problem with CDK's integ-runner breaking the python path and current working directory.
Home-page: https://github.com/tomharvey/cdk-integ-runner-cwd-fix
License: MIT
Keywords: cdk,aws-cdk,aws,testing,test
Author: Tom Harvey
Author-email: tom@alush.co.uk
Requires-Python: >=3.8,<4.0
Classifier: Environment :: Console
Classifier: License :: OSI Approved :: MIT License
Classifier: Operating System :: OS Independent
Classifier: Programming Language :: Python :: 3
Classifier: Programming Language :: Python :: 3.8
Classifier: Programming Language :: Python :: 3.9
Classifier: Programming Language :: Python :: 3.10
Classifier: Programming Language :: Python :: 3.11
Classifier: Programming Language :: Python :: 3.12
Classifier: Topic :: Software Development :: Documentation
Classifier: Topic :: Software Development :: Libraries :: Python Modules
Classifier: Topic :: Software Development :: Quality Assurance
Project-URL: Repository, https://github.com/tomharvey/cdk-integ-runner-cwd-fix
